mdirtree/__init__.py
mdirtree/_version.py
mdirtree/cli.py
mdirtree/generator.py
mdirtree/examples/rest_examples.py
mdirtree/rest/client.py
mdirtree/rest/server.py
mdirtree-0.1.6.dist-info/licenses/LICENSE
mdirtree-0.1.6.dist-info/METADATA
mdirtree-0.1.6.dist-info/WHEEL
mdirtree-0.1.6.dist-info/entry_points.txt
mdirtree-0.1.6.dist-info/top_level.txt
mdirtree-0.1.6.dist-info/RECORD
